{"tours": [
    {"name": "Hohe Kisten", 
        "urls": ["http://de.wikipedia.org/wiki/Hohe_Kisten", "http://www.hikr.org/tour/post17914.html"], 
        "tags": ["easy", "done" ]},
    {"name": "Krottenkopf", "tags": ["easy", "todo"]},
    {"name": "Bischof", "tags": ["easy"]},
    {"name": "Geigelstein", "tags": ["easy", "done_2013"]},
    {"name": "Geierstein", "tags": ["easy", "done_2011" ]},
    {"name": "Klammspitze", "tags": ["easy", "done_2011" ]},
    {"name": "Kreuzspitze", "tags": ["easy", "done_2011" ]},
    {"name": "Fockenstein", "tags": ["easy", "done_2011" ]},
    {"name": "Bärenkopf", "tags": ["easy", "done_2011" ]},
    {"name": "Rotwand via Bayerischzell", "tags": ["easy"]},
    {"name": "Seven Summits von der Rapoldplatte über den Wendelstein zum Bockstein", "tags": ["todo"]},
    {"name": "Bärenkopf", "tags": ["easy"]},
    {"name": "Brecherspitz", "tags": ["easy"]},
    {"name": "Bodenschneid", "tags": ["easy", "done_2013"]},
    {"name": "Rabenkopf", "tags": ["easy", "done_2011", "bike and hike"]},
    {"name": "Guffert", "tags": ["done", "done_2012", "done_2011"]},
    {"name": "Hoher Fricken", "tags": ["done_2012"]},
    {"name": "Aiplspitz", "tags": ["done_2012", "done_2011"]},
    {"name": "Leonhardstein", "tags": ["done_2012"]},
    {"name": "Gamsjoch", "tags": ["done_2011"]},
    {"name": "Mittenwalder Höhenweg", "tags": ["done_2011", "via ferrata"]},
    {"name": "Schinder", "tags": ["done", "done_2011"]},
    {"name": "Halserspitze über den Blauberggrad", "tags": ["done"]},
    {"name": "vom Heimgarten zum Herzogstand", "tags": ["done_2012"]},
    {"name": "Mondscheinspitze", "tags": ["done_2011"]},
    {"name": "Ammergauer Hochplatte", "tags": ["done_2012"]},
    {"name": "Wank", "tags": ["done", "done_2011"]},
    {"name": "Notkarspitze", "tags": ["done"]},
    {"name": "Kramer", "tags": ["done"]},
    {"name": "Hoher Ziegspitz", "tags": ["done"]},
    {"name": "ettaler Mandl", "tags": ["done"]},
    {"name": "Zugspitze", "tags": ["todo"]},
    {"name": "Hohe Munde", "tags": ["todo"]},
    {"name": "Elmauer Halt", "tags": ["todo"]},
    {"name": "Goinger Halt", "tags": ["todo"]},
    {"name": "Treffauer", "tags": ["todo"]},
    {"name": "Daniel", "tags": ["todo"]},
    {"name": "Birkkarspitze", "tags": ["todo"]},
    {"name": "Lamsenspitze", "tags": ["todo"]},
    {"name": "Watzmann Überschreitung", "tags": ["todo", "difficult"]},
    {"name": "Ehrwalder Sonnenspitze", "tags": ["todo", "difficult"]},
    {"name": "Hindelanger Klettersteig", "tags": ["todo", "via ferrata"]},
    {"name": "Mindelheimer Klettersteig", "tags": ["todo", "via ferrata"]},
    {"name": "Upsspitze", "tags": ["todo"]},
    {"name": "Hochschrutte", "tags": ["todo"]},
    {"name": "Triglav", "tags": ["todo", "long"]}
]}
